rasahub_google_calendar/__init__.py
rasahub_google_calendar-0.3.2.dist-info/METADATA
rasahub_google_calendar-0.3.2.dist-info/RECORD
rasahub_google_calendar-0.3.2.dist-info/WHEEL
rasahub_google_calendar-0.3.2.dist-info/top_level.txt
