Metadata-Version: 2.1
Name: rasahub-google-calendar
Version: 0.3.2
Summary: Rasa connector for Google Calendar
Home-page: http://github.com/frommie/rasahub-google-calendar
Author: Christian Frommert
Author-email: christian.frommert@gmail.com
License: MIT
Keywords: rasahub
Platform: UNKNOWN
Classifier: Development Status :: 3 - Alpha
Classifier: Intended Audience :: Developers
Classifier: License :: OSI Approved :: MIT License
Classifier: Programming Language :: Python :: 2.7
Classifier: Topic :: Software Development
Provides-Extra: test
Requires-Dist: rasahub
Requires-Dist: authlib
Requires-Dist: flask
Requires-Dist: google-api-python-client
Provides-Extra: test
